mojicopy/__init__.py
mojicopy/ai_emoji.py
mojicopy/cli.py
mojicopy/emoji_unicode.py
mojicopy/random_emoji.py
mojicopy/settings.py
mojicopy-1.1.0.dist-info/LICENSE
mojicopy-1.1.0.dist-info/METADATA
mojicopy-1.1.0.dist-info/WHEEL
mojicopy-1.1.0.dist-info/entry_points.txt
mojicopy-1.1.0.dist-info/top_level.txt
mojicopy-1.1.0.dist-info/RECORD
