Metadata-Version: 2.1
Name: mojicopy
Version: 1.1.0
Summary: Tool to generate emojis from text prompts stored in the clipboard using OpenAI.
Home-page: https://mojicopy.com
Author: Alexander Tkachev
Author-email: sasha64sasha@gmail.com
Keywords: emoji,clipboard,openai,ChatGPT
Classifier: Intended Audience :: Information Technology
Classifier: Intended Audience :: System Administrators
Classifier: Intended Audience :: Developers
Classifier: License :: OSI Approved :: Apache Software License
Classifier: Development Status :: 5 - Production/Stable
Classifier: Operating System :: OS Independent
Classifier: Programming Language :: Python :: 3
Classifier: Programming Language :: Python :: 3.7
Classifier: Programming Language :: Python :: 3.8
Classifier: Programming Language :: Python :: 3.9
Classifier: Programming Language :: Python :: 3.10
License-File: LICENSE
Requires-Dist: openai
Requires-Dist: xerox
Requires-Dist: typer
